listparser/__init__.py
listparser/common.py
listparser/dates.py
listparser/exceptions.py
listparser/foaf.py
listparser/igoogle.py
listparser/opml.py
listparser/py.typed
listparser/xml_handler.py
listparser-0.20.dist-info/LICENSE.txt
listparser-0.20.dist-info/METADATA
listparser-0.20.dist-info/WHEEL
listparser-0.20.dist-info/RECORD
