Metadata-Version: 2.1
Name: listparser
Version: 0.20
Summary: Parse OPML subscription lists
Home-page: https://github.com/kurtmckee/listparser/
License: MIT
Keywords: opml,foaf,igoogle,feed
Author: Kurt McKee
Author-email: contactme@kurtmckee.org
Requires-Python: >=3.8
Classifier: Development Status :: 5 - Production/Stable
Classifier: Intended Audience :: Developers
Classifier: License :: OSI Approved :: MIT License
Classifier: Programming Language :: Python :: 3
Classifier: Programming Language :: Python :: 3.8
Classifier: Programming Language :: Python :: 3.9
Classifier: Programming Language :: Python :: 3.10
Classifier: Programming Language :: Python :: 3.11
Classifier: Programming Language :: Python :: 3.12
Classifier: Topic :: Text Processing :: Markup :: XML
Provides-Extra: http
Provides-Extra: lxml
Requires-Dist: lxml (>=4.6.2,<6.0.0) ; extra == "lxml"
Requires-Dist: requests (>=2.25.1,<3.0.0) ; extra == "http"
Project-URL: Documentation, https://listparser.readthedocs.io/en/latest/
Project-URL: Repository, https://github.com/kurtmckee/listparser/
